tts_webui_extension/demucs/__init__.py
tts_webui_extension/demucs/main.py
tts_webui_extension_demucs-0.0.4.dist-info/licenses/LICENSE
tts_webui_extension_demucs-0.0.4.dist-info/METADATA
tts_webui_extension_demucs-0.0.4.dist-info/WHEEL
tts_webui_extension_demucs-0.0.4.dist-info/top_level.txt
tts_webui_extension_demucs-0.0.4.dist-info/RECORD
