Metadata-Version: 2.4
Name: tts_webui_extension.demucs
Version: 0.0.4
Summary: Demucs is a music source separation model that can separate drums, bass, vocals, and other instruments
Home-page: https://github.com/rsxdalv/tts_webui_extension.demucs
Author: rsxdalv
Classifier: Programming Language :: Python :: 3
Classifier: License :: OSI Approved :: MIT License
Classifier: Operating System :: OS Independent
License-File: LICENSE
Requires-Dist: demucs
Requires-Dist: torchaudio>=2.0.0
Dynamic: author
Dynamic: classifier
Dynamic: description
Dynamic: description-content-type
Dynamic: home-page
Dynamic: license-file
Dynamic: requires-dist
Dynamic: summary
